Workbook
Name aporte: Sheet1!$D$17
Name patrimonio: Sheet1!$D$20
Name qta_anos: Sheet1!$D$18
Name rendimento_carteira: Sheet1!$D$13
Name salario: Sheet1!$D$12
Name sugestao_investimento: Sheet1!$D$14
Name taxa_mensal: Sheet1!$D$19

Sheet Sheet1
B11: CONFIGURAÇÕES
B12: Salário | D12: 1500
B13: Rendimento Carteira | D13: 0.009
B14: Sugestão de Investimento | D14: =D12*30% -> 450
B16: INVESTIMENTO MENSAL
B17: Quanto investir por mês? | D17: 500
B18: Por quantos anos? | D18: 5
B19: Taxa de rendimento mensal? | D19: 0.01079
B20: Patrimônio acumulado? | D20: =FV(taxa_mensal,qta_anos*12,aporte*-1) -> 41888.457
B21: Dvidendos mensais? | D21: =patrimonio*rendimento_carteira -> 376.99611
B23: Cenários | D23: Dividendo
A24: 2 | B24: Quantos em 2 anos? | C24: =FV($D$19,$A24*12,$D$17*-1) -> 13613.814 | D24: =C24*rendimento_carteira -> 122.52432
A25: 5 | B25: Quantos em 5 anos? | C25: =FV($D$19,$A25*12,$D$17*-1) -> 41888.457 | D25: =C25*rendimento_carteira -> 376.99611
A26: 10 | B26: Quantos em 10 anos? | C26: =FV($D$19,$A26*12,$D$17*-1) -> 121642.11 | D26: =C26*rendimento_carteira -> 1094.779
A27: 20 | B27: Quantos em 20 anos? | C27: =FV($D$19,$A27*12,$D$17*-1) -> 562599.2 | D27: =C27*rendimento_carteira -> 5063.3928
A28: 30 | B28: Quantos em 30 anos? | C28: =FV($D$19,$A28*12,$D$17*-1) -> 2161084.8 | D28: =C28*rendimento_carteira -> 19449.763
B32: Perfil | C32: Conservador
B33: Valor a ser investido por mês | C33: =aporte -> 500
B35: Tipo de FII | C35: Percentual Sugerido | D35: Valores
B36: Papel | C36: =VLOOKUP($C$32&"-"&B36,Sheet2!A$1:D$20,4,FALSE) -> 0.3 | D36: =C36*$C$33 -> 150
B37: Tijolo | C37: =VLOOKUP($C$32&"-"&B37,Sheet2!A$1:D$20,4,FALSE) -> 0.5 | D37: =C37*$C$33 -> 250
B38: Híbridos | C38: =VLOOKUP($C$32&"-"&B38,Sheet2!A$1:D$20,4,FALSE) -> 0.1 | D38: =C38*$C$33 -> 50
B39: FOFs | C39: =VLOOKUP($C$32&"-"&B39,Sheet2!A$1:D$20,4,FALSE) -> 0.1 | D39: =C39*$C$33 -> 50
B40: Desenvolvimento | C40: =VLOOKUP($C$32&"-"&B40,Sheet2!A$1:D$20,4,FALSE) -> 0 | D40: =C40*$C$33 -> 0
B41: Hotelarias | C41: =VLOOKUP($C$32&"-"&B41,Sheet2!A$1:D$20,4,FALSE) -> 0 | D41: =C41*$C$33 -> 0
D42: =SUM(D36:D41) -> 500

Sheet Sheet2
A2: CHAVE | B2: Perfil | C2: Tipode de FII | D2: %
A3: =B3&"-"&C3 -> Conservador-Papel | B3: Conservador | C3: Papel | D3: 0.3 | I3: %
A4: =B4&"-"&C4 -> Conservador-Tijolo | B4: Conservador | C4: Tijolo | D4: 0.5 | H4: Moderado-Tijolo | I4: =VLOOKUP(H4,$A:$D,4,FALSE) -> 0.35
A5: =B5&"-"&C5 -> Conservador-Híbridos | B5: Conservador | C5: Híbridos | D5: 0.1
A6: =B6&"-"&C6 -> Conservador-FOFs | B6: Conservador | C6: FOFs | D6: 0.1
A7: =B7&"-"&C7 -> Conservador-Desenvolvimento | B7: Conservador | C7: Desenvolvimento | D7: 0
A8: =B8&"-"&C8 -> Conservador-Hotelarias | B8: Conservador | C8: Hotelarias | D8: 0
A9: =B9&"-"&C9 -> Moderado-Papel | B9: Moderado | C9: Papel | D9: 0.32
A10: =B10&"-"&C10 -> Moderado-Tijolo | B10: Moderado | C10: Tijolo | D10: 0.35
A11: =B11&"-"&C11 -> Moderado-Híbridos | B11: Moderado | C11: Híbridos | D11: 0.08
A12: =B12&"-"&C12 -> Moderado-FOFs | B12: Moderado | C12: FOFs | D12: 0.05
A13: =B13&"-"&C13 -> Moderado-Desenvolvimento | B13: Moderado | C13: Desenvolvimento | D13: 0.1
A14: =B14&"-"&C14 -> Moderado-Hotelarias | B14: Moderado | C14: Hotelarias | D14: 0.1
A15: =B15&"-"&C15 -> Agressivo-Papel | B15: Agressivo | C15: Papel | D15: 0.5
A16: =B16&"-"&C16 -> Agressivo-Tijolo | B16: Agressivo | C16: Tijolo | D16: 0.1
... A20: =B20&"-"&C20 -> Agressivo-Hotelarias | B20: Agressivo | C20: Hotelarias | D20: 0.1
